pyzernike/_core.cpython-311-darwin.so
zernike_descriptors-0.1.0.dist-info/METADATA
zernike_descriptors-0.1.0.dist-info/WHEEL
zernike_descriptors-0.1.0.dist-info/licenses/LICENSE
zernike_descriptors-0.1.0.dist-info/RECORD
