Metadata-Version: 2.1
Name: zernike_descriptors
Version: 0.1.0
Summary: A Python package to compute 3D zernike descriptors.
Author-Email: Valentin Maurer <valentin.maurer@embl-hamburg.de>
Classifier: Programming Language :: Python :: 3
Classifier: License :: OSI Approved :: MIT License
Classifier: Operating System :: OS Independent
Project-URL: Homepage, https://github.com/maurerv/pyzernike
Requires-Python: >=3.10
